{"name":"Completar alertas","id":"automatizacion-demoqa1;completar-alertas","testSteps":[{"number":1,"description":"Given El usuario ingresa nuevamente al sitio web demoqa.com","duration":42,"startTime":"2024-01-13T23:59:31.827895600-05:00[America/Bogota]","result":"PENDING","precondition":false,"level":0},{"number":2,"description":"When Se dirige al apartado de las alertas","duration":4,"startTime":"2024-01-13T23:59:31.870727400-05:00[America/Bogota]","result":"IGNORED","precondition":false,"level":0},{"number":3,"description":"And Valida las 4 alertas","duration":1,"startTime":"2024-01-13T23:59:31.876238-05:00[America/Bogota]","result":"IGNORED","precondition":false,"level":0},{"number":4,"description":"Then Se verifica la validacion de las alertas","duration":1,"startTime":"2024-01-13T23:59:31.878239500-05:00[America/Bogota]","result":"IGNORED","precondition":false,"level":0}],"userStory":{"id":"automatizacion-demoqa1","storyName":"Automatizacion demoqa1","displayName":"Automatizacion demoqa1","path":"file:///D:/PROYECTOS/Proyectos/demoqa1.com/src/test/resources/feature/demoqa1.feature","narrative":"    Como usuario de la pagina demoqa\n    quiero realizar un click en la opcion \"widgets\"\n    despues en la opcion “Auto Complete”\n    y llenar los campos con las respuestas Black y White respectivamente","type":"feature","qualifiedTag":{"name":"Feature/Automatizacion demoqa1","type":"feature","displayName":"Feature/Automatizacion demoqa1"}},"featureTag":{"name":"Feature/Automatizacion demoqa1","type":"feature","displayName":"Feature/Automatizacion demoqa1"},"title":"Completar alertas","description":"","tags":[{"name":"Windows","type":"context","displayName":"Windows"},{"name":"Second","type":"tag","displayName":"Second"}],"allTags":[{"name":"Windows","type":"context","displayName":"Windows"},{"name":"Second","type":"tag","displayName":"Second"},{"name":"Feature/Automatizacion demoqa1","type":"feature","displayName":"Feature/Automatizacion demoqa1"}],"startTime":"2024-01-13T23:59:31.708147-05:00[America/Bogota]","duration":177,"projectKey":"","annotatedResult":"PENDING","isManualTestingUpToDate":false,"context":"windows","manual":false,"testSource":"Cucumber","actors":[{"name":"Daniel","can":["browse the web"]}],"result":"PENDING"}